[
  {
    "seriesIndex": 1,
    "season": 0,
    "title": "Good News Bad News",
    "airDate": "7/5/89",
    "primarySource": "http://www.seinfeldscripts.com/TheSeinfeldChronicles.htm",
    "indexSource": "http://www.seinfeldscripts.com/seinfeld-scripts.html",
    "generatedAt": "2026-05-13T14:39:16.039Z",
    "questions": [
      {
        "id": 1,
        "type": "who_said",
        "question": "Who says: “Oh, come on now, what are you asking her? Now,”?",
        "options": [
          "I shoot you",
          "WAITRESS",
          "Kramer",
          "JERRY"
        ],
        "correctIndex": 3,
        "answer": "JERRY"
      },
      {
        "id": 2,
        "type": "who_said",
        "question": "Who says: “Do you handle any of that commercial...real estate”?",
        "options": [
          "KRAMER",
          "WAITRESS",
          "LAURA",
          "Jerry"
        ],
        "correctIndex": 0,
        "answer": "KRAMER"
      },
      {
        "id": 3,
        "type": "who_said",
        "question": "Who says: “closes the lid] GEORGE: Look at that: they're done! It's a miracle! [”?",
        "options": [
          "Jerry",
          "George",
          "LAURA",
          "Kramer"
        ],
        "correctIndex": 1,
        "answer": "George"
      },
      {
        "id": 4,
        "type": "who_said",
        "question": "Who says: “sits down next to him and starts turning over the pages of a magazine. Suddenly he spots an article he likes…”?",
        "options": [
          "JERRY",
          "Kramer",
          "LAURA",
          "GEORGE"
        ],
        "correctIndex": 1,
        "answer": "Kramer"
      },
      {
        "id": 5,
        "type": "who_said",
        "question": "Who says: “, it's signals! Don't you....all right. Did she even ask you, what you were doin' tomorrow night, if you were…”?",
        "options": [
          "Jerry",
          "Kramer",
          "WAITRESS",
          "Let's face it"
        ],
        "correctIndex": 0,
        "answer": "Jerry"
      },
      {
        "id": 6,
        "type": "who_said",
        "question": "Who says: “are waiting for Laura] JERRY: Wouldn't it be great if you could ask a woman what she's thinking? GEORGE: What…”?",
        "options": [
          "WAITRESS",
          "JERRY",
          "LAURA",
          "George"
        ],
        "correctIndex": 3,
        "answer": "George"
      },
      {
        "id": 7,
        "type": "who_said",
        "question": "Who says: “I'm aware of you, all right, let's go [opens the bathroom”?",
        "options": [
          "LAURA",
          "GEORGE",
          "Kramer",
          "Let's face it"
        ],
        "correctIndex": 1,
        "answer": "GEORGE"
      },
      {
        "id": 8,
        "type": "who_said",
        "question": "Who says: “Jerry? I have to tell ya somethin':...this is the dullest”?",
        "options": [
          "LAURA",
          "GEORGE",
          "I shoot you",
          "WAITRESS"
        ],
        "correctIndex": 1,
        "answer": "GEORGE"
      },
      {
        "id": 9,
        "type": "who_said",
        "question": "Who says: “What, are you serious...why, why did she call”?",
        "options": [
          "LAURA",
          "I shoot you",
          "Kramer",
          "JERRY"
        ],
        "correctIndex": 3,
        "answer": "JERRY"
      },
      {
        "id": 10,
        "type": "who_said",
        "question": "Who says: “looks at him with a \"what-the-h...-are-you-doing-look\" and”?",
        "options": [
          "George",
          "CLAIRE",
          "Kramer",
          "Jerry"
        ],
        "correctIndex": 3,
        "answer": "Jerry"
      },
      {
        "id": 11,
        "type": "who_said",
        "question": "Who says: “...How's the real estate-business”?",
        "options": [
          "Jerry",
          "KRAMER",
          "LAURA",
          "Let's face it"
        ],
        "correctIndex": 1,
        "answer": "KRAMER"
      },
      {
        "id": 12,
        "type": "who_said",
        "question": "Who says: “and, and maybe she'll see me when”?",
        "options": [
          "Jerry",
          "WAITRESS",
          "I shoot you",
          "GEORGE"
        ],
        "correctIndex": 3,
        "answer": "GEORGE"
      },
      {
        "id": 13,
        "type": "who_said",
        "question": "Who says: “Oh, you don't recall”?",
        "options": [
          "I shoot you",
          "JERRY",
          "KRAMER",
          "Let's face it"
        ],
        "correctIndex": 1,
        "answer": "JERRY"
      },
      {
        "id": 14,
        "type": "who_said",
        "question": "Who says: “You're a back-up, you're a second-line, a just-in-case,”?",
        "options": [
          "I shoot you",
          "JERRY",
          "GEORGE",
          "CLAIRE"
        ],
        "correctIndex": 2,
        "answer": "GEORGE"
      },
      {
        "id": 15,
        "type": "scene_setting",
        "question": "Which setting appears as a scripted scene heading in this episode?",
        "options": [
          "Airport. Jerry and George are waiting for Laura",
          "Comedy club.",
          "Comedy club",
          "Jerry's apartment. Jerry and George enter, lifting a heavy mattress"
        ],
        "correctIndex": 0,
        "answer": "Airport. Jerry and George are waiting for Laura"
      },
      {
        "id": 16,
        "type": "scene_setting",
        "question": "Which setting appears as a scripted scene heading in this episode?",
        "options": [
          "Comedy club.",
          "Airport. Jerry and George are waiting for Laura",
          "Jerry's apartment. Jerry and George enter, lifting a heavy mattress",
          "Pete's luncheonette. Jerry and George are sitting at a table."
        ],
        "correctIndex": 0,
        "answer": "Comedy club."
      },
      {
        "id": 17,
        "type": "scene_setting",
        "question": "Which setting appears as a scripted scene heading in this episode?",
        "options": [
          "Jerry's apartment. Jerry shows Laura the apartment",
          "Comedy club.",
          "Jerry's apartment. Jerry is watching TV",
          "Jerry's apartment. Jerry and George enter, lifting a heavy mattress"
        ],
        "correctIndex": 3,
        "answer": "Jerry's apartment. Jerry and George enter, lifting a heavy mattress"
      },
      {
        "id": 18,
        "type": "scene_setting",
        "question": "Which setting appears as a scripted scene heading in this episode?",
        "options": [
          "Comedy club",
          "Jerry's apartment. Jerry and George enter, lifting a heavy mattress",
          "Laundry. Jerry and George are there; George is staring at one of the dryers",
          "Jerry's apartment. Jerry is watching TV"
        ],
        "correctIndex": 0,
        "answer": "Comedy club"
      },
      {
        "id": 19,
        "type": "scene_setting",
        "question": "Which setting appears as a scripted scene heading in this episode?",
        "options": [
          "Comedy club",
          "Jerry's apartment. Jerry is watching TV",
          "Comedy club.",
          "Pete's luncheonette. Jerry and George are sitting at a table."
        ],
        "correctIndex": 3,
        "answer": "Pete's luncheonette. Jerry and George are sitting at a table."
      },
      {
        "id": 20,
        "type": "scene_setting",
        "question": "Which setting appears as a scripted scene heading in this episode?",
        "options": [
          "Jerry's apartment. Jerry shows Laura the apartment",
          "Airport. Jerry and George are waiting for Laura",
          "Pete's luncheonette. Jerry and George are sitting at a table.",
          "Comedy club"
        ],
        "correctIndex": 0,
        "answer": "Jerry's apartment. Jerry shows Laura the apartment"
      },
      {
        "id": 21,
        "type": "cast",
        "question": "In the cast list, who plays “fine”?",
        "options": [
          "no, we're goin' on a boat-ride...don't be silly...I'm not",
          "the dryer is their only chance to escape and they",
          "look I, I'll call you tomorrow...OK,",
          "The car-horn-honk, is"
        ],
        "correctIndex": 0,
        "answer": "no, we're goin' on a boat-ride...don't be silly...I'm not"
      },
      {
        "id": 22,
        "type": "cast",
        "question": "In the cast list, who plays “talking about.”?",
        "options": [
          "this whole thing, we're all out now, no one is home.",
          "no, think about it: the washing machine",
          "no, I, I'm gonna stay here tomorrow...yes, yes it's",
          "no, we're goin' on a boat-ride...don't be silly...I'm not"
        ],
        "correctIndex": 0,
        "answer": "this whole thing, we're all out now, no one is home."
      },
      {
        "id": 23,
        "type": "cast",
        "question": "In the cast list, who plays “our staff is on the scene.”?",
        "options": [
          "no, we're goin' on a boat-ride...don't be silly...I'm not",
          "The car-horn-honk, is",
          "That's why, I think, men get frustrated,",
          "! [Jerry is laughing, Claire walks away"
        ],
        "correctIndex": 2,
        "answer": "That's why, I think, men get frustrated,"
      },
      {
        "id": 24,
        "type": "meta_series",
        "question": "On the SeinfeldScripts master episode list, which series episode number is this installment?",
        "options": [
          "8",
          "2",
          "1",
          "11"
        ],
        "correctIndex": 2,
        "answer": "1"
      },
      {
        "id": 25,
        "type": "meta_season",
        "question": "On SeinfeldScripts.com, this episode is grouped under which season header?",
        "options": [
          "Season 0",
          "Season 1"
        ],
        "correctIndex": 0,
        "answer": "Season 0"
      }
    ]
  }
]